klog/__init__.py
klog/admin_client.py
klog/client.py
klog/cli/__init__.py
klog/cli/models.py
klog/cli/sender.py
klog/cli/worker.py
klog/common/__init__.py
klog/common/abstract_client.py
klog/common/abstract_model.py
klog/common/auth.py
klog/common/common_client.py
klog/common/compress.py
klog/common/const.py
klog/common/converters.py
klog/common/counter.py
klog/common/credential.py
klog/common/down_sampler.py
klog/common/k_http.py
klog/common/k_logger.py
klog/common/k_queue.py
klog/common/mock.py
klog/common/rate_limit.py
klog/common/signer.py
klog/common/snowflake.py
klog/common/exception/__init__.py
klog/common/exception/exceptions.py
klog/common/exception/klog_exception.py
klog/common/khttp/__init__.py
klog/common/khttp/request.py
klog/common/profile/__init__.py
klog/common/profile/client_profile.py
klog/common/profile/http_profile.py
klog/common/protobuf/__init__.py
klog/common/protobuf/klog_pb2.py
klog_sdk-0.9.2.dist-info/LICENSE
klog_sdk-0.9.2.dist-info/METADATA
klog_sdk-0.9.2.dist-info/WHEEL
klog_sdk-0.9.2.dist-info/top_level.txt
klog_sdk-0.9.2.dist-info/RECORD
