Metadata-Version: 2.1
Name: klog-sdk
Version: 0.9.2
Summary: Kingsoft Log Service SDK
Home-page: https://gitee.com/klogsdk/klog-python-sdk
Author: KLog Developers
Author-email: ksc-klog@kingsoft.com
License: MIT
Keywords: klog,klog-sdk,kingsoft-cloud,klog-python-sdk
Classifier: Development Status :: 5 - Production/Stable
Classifier: Intended Audience :: Developers
Classifier: License :: OSI Approved :: MIT License
Classifier: Operating System :: OS Independent
Classifier: Programming Language :: Python :: 2.7
Classifier: Programming Language :: Python :: 3
Requires-Python: >=2.7
License-File: LICENSE
Requires-Dist: protobuf ==3.17.3
Requires-Dist: lz4
Requires-Dist: requests ~=2.27.1
